gitscaffold-0.3.0.dist-info/licenses/LICENSE
scaffold/__init__.py
scaffold/__main__.py
scaffold/ai.py
scaffold/cli.py
scaffold/github.py
scaffold/main.py
scaffold/parser.py
scaffold/validator.py
scaffold/scripts/__init__.py
scaffold/scripts/import_md.py
scaffold/templates/__init__.py
scripts/__init__.py
scripts/delete_closed.py
scripts/enrich.py
scripts/github_roadmap_setup.py
scripts/import_md.py
scripts/update_coverage.py
gitscaffold-0.3.0.dist-info/METADATA
gitscaffold-0.3.0.dist-info/WHEEL
gitscaffold-0.3.0.dist-info/entry_points.txt
gitscaffold-0.3.0.dist-info/top_level.txt
gitscaffold-0.3.0.dist-info/RECORD
