Metadata-Version: 2.4
Name: gitscaffold
Version: 0.3.0
Summary: Convert roadmaps to GitHub issues
License-Expression: MIT
Requires-Python: >=3.8
License-File: LICENSE
Requires-Dist: PyGithub>=1.55
Requires-Dist: click>=8.0
Requires-Dist: jinja2>=3.0
Requires-Dist: pydantic>=1.9
Requires-Dist: openai<2.0.0,>=1.0.0
Requires-Dist: python-dotenv>=0.20.0
Requires-Dist: rich>=13.0.0
Requires-Dist: streamlit>=1.20.0
Requires-Dist: uvicorn[standard]>=0.20.0
Dynamic: license-file
